README.md
setup.cfg
setup.py
scrapy_sqlitem/__init__.py
scrapy_sqlitem/sqlitem.py
scrapy_sqlitem/sqlspider.py
scrapy_sqlitem.egg-info/PKG-INFO
scrapy_sqlitem.egg-info/SOURCES.txt
scrapy_sqlitem.egg-info/dependency_links.txt
scrapy_sqlitem.egg-info/not-zip-safe
scrapy_sqlitem.egg-info/pbr.json
scrapy_sqlitem.egg-info/top_level.txt