Metadata-Version: 1.1
Name: scrapy-sqlitem
Version: 0.1.1
Summary: Scrapy extension to save items to a sql database
Home-page: https://github.com/ryancerf/scrapy-sqlitem
Author: Ryan Cerf
Author-email: ryancerf@yahoo.com
License: BSD
Platform: UNKNOWN
Classifier: Framework :: Scrapy
Classifier: Development Status :: 3 - Alpha
Classifier: Environment :: Console
Classifier: Intended Audience :: Developers
Classifier: License :: OSI Approved :: BSD License
Classifier: Operating System :: OS Independent
Classifier: Programming Language :: Python
Classifier: Programming Language :: Python :: 2
Classifier: Programming Language :: Python :: 2.7
Classifier: Topic :: Utilities
Classifier: Framework :: Scrapy
Requires: scrapy (>=0.24.5)
Requires: sqlalchemy
